iplocalize/__init__.py
iplocalize/cmd.py
iplocalize/localize.py
iplocalize-0.0.2.dist-info/LICENSE
iplocalize-0.0.2.dist-info/METADATA
iplocalize-0.0.2.dist-info/WHEEL
iplocalize-0.0.2.dist-info/entry_points.txt
iplocalize-0.0.2.dist-info/top_level.txt
iplocalize-0.0.2.dist-info/RECORD
