Metadata-Version: 2.1
Name: iplocalize
Version: 0.0.2
Summary: Localize and test a given freeproxy
Home-page: https://github.com/ylmrx/iplocalize
Author: Yoann Lamouroux
Author-email: ylamouroux@ubuntu.com
License: UNKNOWN
Platform: UNKNOWN
Classifier: Programming Language :: Python :: 3
Classifier: License :: OSI Approved :: MIT License
Classifier: Operating System :: OS Independent
Requires-Dist: requests
Requires-Dist: geoip2
Requires-Dist: pygments
